StockFactor/Risk_factor.py
StockFactor/__init__.py
StockFactor-0.1.0.dist-info/LICENSE
StockFactor-0.1.0.dist-info/METADATA
StockFactor-0.1.0.dist-info/WHEEL
StockFactor-0.1.0.dist-info/top_level.txt
StockFactor-0.1.0.dist-info/RECORD
